smart_meter_texas/__init__.py
smart_meter_texas/const.py
smart_meter_texas/exceptions.py
smart_meter_texas-0.5.3.dist-info/AUTHORS.rst
smart_meter_texas-0.5.3.dist-info/LICENSE
smart_meter_texas-0.5.3.dist-info/METADATA
smart_meter_texas-0.5.3.dist-info/WHEEL
smart_meter_texas-0.5.3.dist-info/top_level.txt
smart_meter_texas-0.5.3.dist-info/RECORD
