Metadata-Version: 2.1
Name: smart-meter-texas
Version: 0.5.3
Summary: Package to connect to and retrieve data from the unofficial Smart Meter Texas API
Home-page: https://github.com/grahamwetzler/smart-meter-texas
Author: Graham Wetzler
Author-email: graham@wetzler.dev
License: MIT license
Keywords: smart_meter_texas
Classifier: Development Status :: 2 - Pre-Alpha
Classifier: Intended Audience :: Developers
Classifier: License :: OSI Approved :: MIT License
Classifier: Natural Language :: English
Classifier: Programming Language :: Python :: 3
Classifier: Programming Language :: Python :: 3.6
Classifier: Programming Language :: Python :: 3.7
Classifier: Programming Language :: Python :: 3.8
Requires-Python: >=3.6
License-File: LICENSE
License-File: AUTHORS.rst
Requires-Dist: aiohttp (<4,>=3.7.4)
Requires-Dist: asn1 (>=2.4.1)
Requires-Dist: python-dateutil (>=2.8.1)
Requires-Dist: tenacity (>=8.0.1)
